{
  "features": {
    "Age": 31,
    "Attrition": 0.0,
    "BusinessTravel": "Non-Travel",
    "DailyRate": 697,
    "Department": "Research_Development",
    "DistanceFromHome": 10,
    "Education": "Bachelor",
    "EducationField": "Medical",
    "EnvironmentSatisfaction": "High",
    "Gender": "Female",
    "HourlyRate": 40,
    "JobInvolvement": "High",
    "JobLevel": 3,
    "JobRole": "Research_Director",
    "JobSatisfaction": "High",
    "MaritalStatus": "Married",
    "MonthlyIncome": 11031,
    "MonthlyRate": 26862,
    "NumCompaniesWorked": 4,
    "OverTime": "No",
    "PercentSalaryHike": 20,
    "PerformanceRating": "Outstanding",
    "RelationshipSatisfaction": "High",
    "StockOptionLevel": 1,
    "TotalWorkingYears": 13,
    "TrainingTimesLastYear": 2,
    "WorkLifeBalance": "Best",
    "YearsAtCompany": 11,
    "YearsInCurrentRole": 7,
    "YearsSinceLastPromotion": 4,
    "YearsWithCurrManager": 8
  }
}